{
    "events": [
        {
            "event_type": "JOIN_WORLD",
            "target": "ALL_PLAYERS",
            "noDeathDim": "true",
            "joinOneEver": "true",
            "tasks": [
                {
                    "task_type": "INVENTORY_ADD",
                    "target_type": "SELF",
                    "target": "",
                    "modid": "CompactMachines",
                    "name": "psd",
                    "meta": "0",
                    "count": "1"
                },
                {
                    "task_type": "INVENTORY_ADD",
                    "target_type": "SELF",
                    "target": "",
                    "modid": "HardcoreQuesting",
                    "name": "quest_book",
                    "meta": "0",
                    "count": "1"
                }
            ]
        },
        {
            "event_type": "CHAT",
            "text": "!buy kini",
            "tasks": [
                {
                    "task_type": "INVENTORY_ADD",
                    "target_type": "ONE_PLAYER",
                    "target": "Runew0lf",
                    "modid": "Mankini",
                    "name": "itemDyeableMankini",
                    "meta": "0",
                    "count": "1",
                    "nbt": "{ench:[{id:0,lvl:4},{id:8,lvl:1}]}",
                    "condtions": [
                        {
                            "condition_type": "INVENTORY",
                            "reversed": "true",
                            "modid": "Mankini",
                            "name": "itemDyeableMankini",
                            "meta": "0"
                        }
                    ]
                }
            ]
        }
    ]
}